syncthing/__init__.py
syncthing/meta.py
python_syncthing_client-0.1.1.dist-info/LICENSE
python_syncthing_client-0.1.1.dist-info/WHEEL
python_syncthing_client-0.1.1.dist-info/METADATA
python_syncthing_client-0.1.1.dist-info/RECORD
